{
  "formatVersion": 1,
  "database": {
    "version": 1,
    "identityHash": "adb1e61e027d040e34799045ab9fba95",
    "entities": [
      {
        "tableName": "documents",
        "createSql": "CREATE TABLE IF NOT EXISTS `${TABLE_NAME}` (`id` INTEGER PRIMARY KEY AUTOINCREMENT NOT NULL, `uid` TEXT NOT NULL, `name` TEXT NOT NULL, `uri` TEXT NOT NULL, `size` INTEGER NOT NULL, `date_created` INTEGER NOT NULL, `date_modified` INTEGER, `preview_image_uri` TEXT, `folder_id` INTEGER, FOREIGN KEY(`folder_id`) REFERENCES `folders`(`id`) ON UPDATE CASCADE ON DELETE SET NULL )",
        "fields": [
          {
            "fieldPath": "id",
            "columnName": "id",
            "affinity": "INTEGER",
            "notNull": true
          },
          {
            "fieldPath": "uid",
            "columnName": "uid",
            "affinity": "TEXT",
            "notNull": true
          },
          {
            "fieldPath": "name",
            "columnName": "name",
            "affinity": "TEXT",
            "notNull": true
          },
          {
            "fieldPath": "uri",
            "columnName": "uri",
            "affinity": "TEXT",
            "notNull": true
          },
          {
            "fieldPath": "size",
            "columnName": "size",
            "affinity": "INTEGER",
            "notNull": true
          },
          {
            "fieldPath": "dateCreated",
            "columnName": "date_created",
            "affinity": "INTEGER",
            "notNull": true
          },
          {
            "fieldPath": "dateModified",
            "columnName": "date_modified",
            "affinity": "INTEGER",
            "notNull": false
          },
          {
            "fieldPath": "previewImageUri",
            "columnName": "preview_image_uri",
            "affinity": "TEXT",
            "notNull": false
          },
          {
            "fieldPath": "folderId",
            "columnName": "folder_id",
            "affinity": "INTEGER",
            "notNull": false
          }
        ],
        "primaryKey": {
          "autoGenerate": true,
          "columnNames": [
            "id"
          ]
        },
        "indices": [
          {
            "name": "index_documents_folder_id",
            "unique": false,
            "columnNames": [
              "folder_id"
            ],
            "orders": [],
            "createSql": "CREATE INDEX IF NOT EXISTS `index_documents_folder_id` ON `${TABLE_NAME}` (`folder_id`)"
          }
        ],
        "foreignKeys": [
          {
            "table": "folders",
            "onDelete": "SET NULL",
            "onUpdate": "CASCADE",
            "columns": [
              "folder_id"
            ],
            "referencedColumns": [
              "id"
            ]
          }
        ]
      },
      {
        "tableName": "scanned_images",
        "createSql": "CREATE TABLE IF NOT EXISTS `${TABLE_NAME}` (`id` INTEGER PRIMARY KEY AUTOINCREMENT NOT NULL, `document_id` INTEGER NOT NULL, `width` INTEGER NOT NULL, `height` INTEGER NOT NULL, `size` INTEGER NOT NULL, `date` INTEGER NOT NULL, `uri` TEXT NOT NULL, `quality` TEXT NOT NULL, FOREIGN KEY(`document_id`) REFERENCES `documents`(`id`) ON UPDATE CASCADE ON DELETE CASCADE )",
        "fields": [
          {
            "fieldPath": "id",
            "columnName": "id",
            "affinity": "INTEGER",
            "notNull": true
          },
          {
            "fieldPath": "documentId",
            "columnName": "document_id",
            "affinity": "INTEGER",
            "notNull": true
          },
          {
            "fieldPath": "width",
            "columnName": "width",
            "affinity": "INTEGER",
            "notNull": true
          },
          {
            "fieldPath": "height",
            "columnName": "height",
            "affinity": "INTEGER",
            "notNull": true
          },
          {
            "fieldPath": "size",
            "columnName": "size",
            "affinity": "INTEGER",
            "notNull": true
          },
          {
            "fieldPath": "date",
            "columnName": "date",
            "affinity": "INTEGER",
            "notNull": true
          },
          {
            "fieldPath": "uri",
            "columnName": "uri",
            "affinity": "TEXT",
            "notNull": true
          },
          {
            "fieldPath": "quality",
            "columnName": "quality",
            "affinity": "TEXT",
            "notNull": true
          }
        ],
        "primaryKey": {
          "autoGenerate": true,
          "columnNames": [
            "id"
          ]
        },
        "indices": [
          {
            "name": "index_scanned_images_document_id",
            "unique": false,
            "columnNames": [
              "document_id"
            ],
            "orders": [],
            "createSql": "CREATE INDEX IF NOT EXISTS `index_scanned_images_document_id` ON `${TABLE_NAME}` (`document_id`)"
          }
        ],
        "foreignKeys": [
          {
            "table": "documents",
            "onDelete": "CASCADE",
            "onUpdate": "CASCADE",
            "columns": [
              "document_id"
            ],
            "referencedColumns": [
              "id"
            ]
          }
        ]
      },
      {
        "tableName": "folders",
        "createSql": "CREATE TABLE IF NOT EXISTS `${TABLE_NAME}` (`id` INTEGER PRIMARY KEY AUTOINCREMENT NOT NULL, `uid` TEXT NOT NULL, `name` TEXT NOT NULL, `date_created` INTEGER NOT NULL, `date_modified` INTEGER, `document_count` INTEGER NOT NULL, `path` TEXT NOT NULL, `parent_path` TEXT NOT NULL, `path_depth` INTEGER NOT NULL)",
        "fields": [
          {
            "fieldPath": "id",
            "columnName": "id",
            "affinity": "INTEGER",
            "notNull": true
          },
          {
            "fieldPath": "uid",
            "columnName": "uid",
            "affinity": "TEXT",
            "notNull": true
          },
          {
            "fieldPath": "name",
            "columnName": "name",
            "affinity": "TEXT",
            "notNull": true
          },
          {
            "fieldPath": "dateCreated",
            "columnName": "date_created",
            "affinity": "INTEGER",
            "notNull": true
          },
          {
            "fieldPath": "dateModified",
            "columnName": "date_modified",
            "affinity": "INTEGER",
            "notNull": false
          },
          {
            "fieldPath": "documentCount",
            "columnName": "document_count",
            "affinity": "INTEGER",
            "notNull": true
          },
          {
            "fieldPath": "path",
            "columnName": "path",
            "affinity": "TEXT",
            "notNull": true
          },
          {
            "fieldPath": "parentPath",
            "columnName": "parent_path",
            "affinity": "TEXT",
            "notNull": true
          },
          {
            "fieldPath": "pathDepth",
            "columnName": "path_depth",
            "affinity": "INTEGER",
            "notNull": true
          }
        ],
        "primaryKey": {
          "autoGenerate": true,
          "columnNames": [
            "id"
          ]
        },
        "indices": [],
        "foreignKeys": []
      }
    ],
    "views": [],
    "setupQueries": [
      "CREATE TABLE IF NOT EXISTS room_master_table (id INTEGER PRIMARY KEY,identity_hash TEXT)",
      "INSERT OR REPLACE INTO room_master_table (id,identity_hash) VALUES(42, 'adb1e61e027d040e34799045ab9fba95')"
    ]
  }
}